mabplotlib/__init__.py
mabplotlib/experiments/Exp10_To_observe_ber_for_linear_detector.py
mabplotlib/experiments/Exp11_To_observe_ber_performance_of_maximum_likelihood.py
mabplotlib/experiments/Exp1_freespacepathloss_vs_distance_graph.py
mabplotlib/experiments/Exp2_Observe_outage_probability_of_Rayleigh_rician_fading.py
mabplotlib/experiments/Exp3_Observe_outage_probability_of_siso_mimo_system.py
mabplotlib/experiments/Exp4_Power_delay_profile_multipath_frequency_selective.py
mabplotlib/experiments/Exp5_ber_performance_of_siso_system_coherent _detection.py
mabplotlib/experiments/Exp6_ber_performance_of_simo_system_with_mrc_egc.py
mabplotlib/experiments/Exp7_ber_performance_of_almouti_stbc.py
mabplotlib/experiments/Exp8_To_observe_channel_capacity_by_spatial_multiplexing_for_mimo.py
mabplotlib/experiments/Exp9_To_observe_ergodic_capacity_for_various_antenna_configureation.py
mabplotlib/experiments/__init__.py
mabplotlib-0.1.0.dist-info/METADATA
mabplotlib-0.1.0.dist-info/WHEEL
mabplotlib-0.1.0.dist-info/top_level.txt
mabplotlib-0.1.0.dist-info/RECORD
