Metadata-Version: 2.4
Name: mabplotlib
Version: 0.1.0
Summary: View and run MIMO experiment codes easily
Author-email: Mayank <youremail@example.com>
License: MIT
Keywords: mimo,wireless,ber,education
Classifier: Programming Language :: Python :: 3
Classifier: License :: OSI Approved :: MIT License
Classifier: Operating System :: OS Independent
Requires-Python: >=3.8
